mcsrvstatus/__init__.py
mcsrvstatus/async_client.py
mcsrvstatus/client.py
mcsrvstatus/exceptions.py
mcsrvstatus/models.py
tests/__init__.py
tests/test_async_client.py
tests/test_client.py
mcsrvstatus-1.0.6.dist-info/METADATA
mcsrvstatus-1.0.6.dist-info/WHEEL
mcsrvstatus-1.0.6.dist-info/top_level.txt
mcsrvstatus-1.0.6.dist-info/RECORD
