Metadata-Version: 2.4
Name: mcsrvstatus
Version: 1.0.6
Summary: Python library for working with the mcsrvstat.us API - a service for checking the status of Minecraft servers
Home-page: https://github.com/Towux/mcsrvstatus
Author: Towux
Author-email: 
License: MIT
Project-URL: Homepage, https://github.com/Towux/mcsrvstatus
Project-URL: Repository, https://github.com/Towux/mcsrvstatus
Project-URL: Issues, https://github.com/Towux/mcsrvstatus/issues
Project-URL: Documentation, https://github.com/Towux/mcsrvstatus#readme
Keywords: minecraft,server,status,api,mcsrvstat,bedrock,java,async
Classifier: Development Status :: 4 - Beta
Classifier: Intended Audience :: Developers
Classifier: Topic :: Games/Entertainment
Classifier: Topic :: Internet :: WWW/HTTP :: Dynamic Content
Classifier: Topic :: Software Development :: Libraries :: Python Modules
Classifier: License :: OSI Approved :: MIT License
Classifier: Programming Language :: Python :: 3
Classifier: Programming Language :: Python :: 3.6
Classifier: Programming Language :: Python :: 3.7
Classifier: Programming Language :: Python :: 3.8
Classifier: Programming Language :: Python :: 3.9
Classifier: Programming Language :: Python :: 3.10
Classifier: Programming Language :: Python :: 3.11
Classifier: Programming Language :: Python :: 3.12
Classifier: Operating System :: OS Independent
Requires-Python: >=3.6
Requires-Dist: requests>=2.25.1
Requires-Dist: aiohttp>=3.8.0
Provides-Extra: dev
Requires-Dist: pytest>=6.0; extra == "dev"
Requires-Dist: pytest-cov>=2.0; extra == "dev"
Requires-Dist: black>=21.0; extra == "dev"
Requires-Dist: flake8>=3.8; extra == "dev"
Requires-Dist: mypy>=0.800; extra == "dev"
Dynamic: home-page
Dynamic: requires-python
